citation_compass/__init__.py
citation_compass/_version.py
citation_compass/citation.py
citation_compass/citation_registry.py
citation_compass/docstring_utils.py
citation_compass/import_utils.py
citation_compass-0.0.6.dist-info/licenses/LICENSE
citation_compass-0.0.6.dist-info/METADATA
citation_compass-0.0.6.dist-info/WHEEL
citation_compass-0.0.6.dist-info/top_level.txt
citation_compass-0.0.6.dist-info/RECORD
