Metadata-Version: 2.4
Name: citation-compass
Version: 0.0.6
Author-email: LINCC Frameworks <lincc-frameworks-team@lists.lsst.org>
License: MIT License
Project-URL: Source Code, https://github.com/lincc-frameworks/citation-compass
Classifier: Development Status :: 4 - Beta
Classifier: License :: OSI Approved :: MIT License
Classifier: Intended Audience :: Developers
Classifier: Intended Audience :: Science/Research
Classifier: Operating System :: OS Independent
Classifier: Programming Language :: Python
Requires-Python: >=3.8
License-File: LICENSE
Provides-Extra: dev
Requires-Dist: asv==0.6.4; extra == "dev"
Requires-Dist: jupyter; extra == "dev"
Requires-Dist: pre-commit; extra == "dev"
Requires-Dist: pytest; extra == "dev"
Requires-Dist: pytest-cov; extra == "dev"
Requires-Dist: ruff; extra == "dev"
Dynamic: license-file
